spoonfed_commonvoice/__init__.py
spoonfed_commonvoice/main.py
spoonfed_commonvoice-0.0.6.dist-info/LICENSE
spoonfed_commonvoice-0.0.6.dist-info/METADATA
spoonfed_commonvoice-0.0.6.dist-info/WHEEL
spoonfed_commonvoice-0.0.6.dist-info/entry_points.txt
spoonfed_commonvoice-0.0.6.dist-info/top_level.txt
spoonfed_commonvoice-0.0.6.dist-info/RECORD
