Metadata-Version: 2.1
Name: spoonfed-commonvoice
Version: 0.0.6
Summary: CLI to generate Anki notes from Mozilla CommonVoice Datasets for language study
Home-page: https://github.com/dallonasnes/spoonfed-commonvoice
Author: Dallon Asnes
Author-email: dallon.asnes@gmail.com
License: UNKNOWN
Platform: UNKNOWN
Classifier: Programming Language :: Python :: 3
Classifier: License :: OSI Approved :: MIT License
Classifier: Operating System :: OS Independent
License-File: LICENSE
Requires-Dist: tqdm (>=4.61.2)
